{
    "key": "burn! burn! burn!",
    "name": "Burn! Burn! Burn!",
    "url": "https://www.aonprd.com/FeatDisplay.aspx?ItemName=Burn!%20Burn!%20Burn!",
    "source":     [
        "Advanced Race Guide pg. 118",
        "Goblins of Golarion pg. 24"
    ],
    "text": "You take the goblin love of arson and fire play to a whole new level.",
    "prerequisites": "Disable Device 1 rank, goblin.",
    "benefit": "You deal an extra 1d4 points of fire damage when you attack with fire from an alchemical or nonmagical source (such as with alchemical fire or torches) and gain a +4 competence bonus on Reflex saving throws made to avoid catching on fire or to put yourself out when on fire. Additional damage caused by this feat does not apply to magical attacks (such as an alchemist’s bomb) or to splash damage.",
    "name_zh": "烧！烧！烧！",
    "text_zh": "你对纵火及玩火的热爱上升到了一个新的高度。",
    "prerequisites_zh": "解除装置1级，地精。",
    "benefit_zh": "当你使用来源于炼金或非魔法的火焰攻击（比如炽火胶或火把）时额外获得1d4火焰伤害，在避免被火灼烧或者扑灭身上火焰时的反射豁免检定获得+4表现加值。该专长造成的额外伤害不适用于魔法性质的攻击（比如炼金术师的炼金炸弹）以及溅射伤害。"
}
