{
    "key": "fateful channel",
    "name": "Fateful Channel",
    "url": "https://www.aonprd.com/FeatDisplay.aspx?ItemName=Fateful%20Channel",
    "source": ["Inner Sea Gods pg. 212"],
    "text": "Your faith not only heals the body, it tugs the strands of fate.",
    "prerequisites": "Channel positive energy 3d6, worshiper of Pharasma.",
    "benefit": "When you channel positive energy to heal living creatures, you grant each creature you heal the ability to roll twice and take the better result on a single attack roll, skill check, or saving throw of their choice within a number of rounds equal to your Charisma bonus (minimum 1). Multiple uses of this ability do not stack, but they do reset the effect’s duration. A creature can only benefit from one instance of this channel effect at a time.",
    "name_zh": "注命引导",
    "prerequisites_zh": "引导正能量3d6，信仰法莱斯玛。",
    "benefit_zh": "当你引导正能量治疗活物时，你可以给予每一个被你所治疗的生物一次机会，让他们在一次攻击投骰，技能检定或豁免投骰时可以骰两次取高。这个效果持续等同于你的魅力调整值轮（至少1轮），这个能力不能通过多次使用而叠加，但是可以因此而重置持续时间。每个生物每次只能获得一个此效果的影响。"
}
