{
    "key": "innate arcana",
    "name": "Innate Arcana",
    "url": "https://www.aonprd.com/FeatDisplay.aspx?ItemName=Innate%20Arcana",
    "source": ["Monster Codex pg. 200"],
    "text": "You can refresh your spell-like abilities by expending spell energy.",
    "prerequisites": "Arcane spellcaster, caster level 4th, serpentfolk.",
    "benefit": "You can expend two arcane spell slots or prepared spells to cast one of your racial spell-like abilities. The level of each expended spell must be equal to or higher than the sorcerer/wizard spell level of the spell-like ability you want to cast.",
    "name_zh": "自生秘法",
    "text_zh": "你可以通过释放自己准备的奥术能量来充盈天生的魔法回路",
    "prerequisites_zh": "奥术施法者，施法者等级4，蛇人。",
    "benefit_zh": "你可以通过消耗两个已准备的法术或是两个法术位来施放一次种族类法术能力。你所消耗的法术的环数不能低于你所欲施放的类法术能力作为法师/术士法术的环数。"
}
