{
    "key": "traditional weapons",
    "name": "Traditional Weapons",
    "url": "https://www.aonprd.com/FeatDisplay.aspx?ItemName=Traditional%20Weapons",
    "descriptors": ["Combat"],
    "source": ["Path of the Hellknight pg. 45"],
    "text": "You’re a master of utilizing simple, time-trusted arms against strange or technological weapons.",
    "prerequisites": "Int 13.",
    "benefit": "You receive a +2 bonus on combat maneuver checks against creatures wielding exotic weapons, firearms, or technological weapons (see <i>Pathfinder Campaign Setting: Technology Guide<\/i>). You also receive a +2 bonus to your CMD whenever an opponent attempts any combat maneuver against you while wielding such a weapon. You gain these bonuses only if you are not wielding an exotic weapon, firearm, or technological weapon.",
    "name_zh": "循常习故",
    "text_zh": "你擅长使用久经磨练的武器对抗特异武器或高科技武器。",
    "prerequisites_zh": "智力13。",
    "benefit_zh": "你对抗使用异种武器、火器或科技武器（参见《Pathfinder战役设定：科技指南TechnologyGuide》）的生物的战技获得+2加值。当使用这些武器的对手试图对你使用任何战技时，你的CMD也获得+2加值。仅在你不使用异种武器、火器或科技武器时才能获得该专长的益处。"
}
