{
    "key": "cataract",
    "name": "Cataract",
    "url": "https://www.aonprd.com/FeatDisplay.aspx?ItemName=Cataract",
    "descriptors": ["Blood Hex"],
    "source": ["Magic Tactics Toolbox pg. 29"],
    "text": "You can curse the eyes of a wounded enemy.",
    "prerequisites": "Int 13, Perception 5 ranks, Use Magic Device 1 rank.",
    "benefit": "As a full-round action, you can curse a creature you’ve dealt damage to since the beginning of your last turn. The creature must succeed at a Fortitude save or its eyes become milky and its vision is obscured. For 1 round, any target the creature makes a ranged touch attack against gains concealment for the purposes of that attack.",
    "special": "A shaman or witch with this blood hex can use it against any creature she has dealt damage to in the past minute. A shaman or witch can use this blood hex as a standard action.",
    "name_zh": "白内障",
    "text_zh": "你能诅咒受伤敌人的眼睛。",
    "prerequisites_zh": "智力13，察觉5级，使用魔法装置1级。",
    "benefit_zh": "以一个整轮动作，你能诅咒一个自你上一轮开始以来被你造成过伤害的敌人。该生物必须通过一个成功的强韧检定，否则它的眼睛变得浑浊，它的视野被遮蔽。一轮内，它远程接触攻击的目标在判定这次攻击时视为拥有隐蔽。",
    "special_zh": "拥有该血巫术的萨满或女巫能将该巫术施加到在上一分钟内被他造成过伤害的敌人，并能以一个标准动作使用该巫术。"
}
