{
    "key": "divine denouncer",
    "name": "Divine Denouncer",
    "url": "https://www.aonprd.com/FeatDisplay.aspx?ItemName=Divine%20Denouncer",
    "source": ["Faiths and Philosophies pg. 7"],
    "text": "You choose to resist rather than serve the gods.",
    "prerequisites": "Divine Defiance.",
    "benefit": "You gain a +2 insight bonus on Bluff, Diplomacy, Intimidate, Knowledge, Perform (oratory), and Sense Motive checks involving any divine spellcaster or outsider that casts spells as a cleric.",
    "prerequisiteKeys": ["divine defiance"]
}
