{
    "key": "kudzu grappler",
    "name": "Kudzu Grappler",
    "url": "https://www.aonprd.com/FeatDisplay.aspx?ItemName=Kudzu%20Grappler",
    "source": ["Ultimate Wilderness pg. 24"],
    "text": "You climb all over creatures you’re grappling like kudzu, blocking their vision.",
    "prerequisites": "Dex 13, Improved Grapple, Improved Unarmed Strike, Greater Grapple, base attack bonus +6, vine leshy.",
    "benefit": "You add an option to blind the grappled creature for 1 round to the list of actions you can take when you succeed at a check to maintain a grapple.",
    "prerequisiteKeys":     [
        "greater grapple",
        "improved grapple",
        "improved unarmed strike"
    ]
}
