{
    "key": "reactive reversion",
    "name": "Reactive Reversion",
    "url": "https://www.aonprd.com/FeatDisplay.aspx?ItemName=Reactive%20Reversion",
    "source": ["Ultimate Wilderness pg. 24"],
    "text": "You can reactively change back to your natural form.",
    "prerequisites": "Dex 13, change shape ability, leshy subtype.",
    "benefit": "You can shift from your alternate form to your natural form as an immediate action using change shape.",
    "normal": "Leshys can shift between forms as a swift action using change shape."
}
