{
    "key": "wings of air",
    "name": "Wings of Air",
    "url": "https://www.aonprd.com/FeatDisplay.aspx?ItemName=Wings%20of%20Air",
    "source": ["Advanced Race Guide pg. 159"],
    "text": "The winds lift you, carrying you where you want to go.",
    "prerequisites": "Airy Step, character level 9th, sylph.",
    "benefit": "Your bonus on saves against effects with the air or electricity descriptors and effects that deal electricity damage increases to +4. In addition, you gain a supernatural fly speed equal to your base speed (good maneuverability). You may only fly with this ability when wearing light armor or no armor.",
    "prerequisiteKeys": ["airy step"],
    "name_zh": "空气之翼",
    "text_zh": "风将你托起，把你带到你想去的地方。",
    "prerequisites_zh": "轻灵步，角色等级9，风元素裔。",
    "benefit_zh": "你在对抗带有〔气〕与〔电〕描述符的效果，以及造成闪电伤害的效果时豁免检定再+2（达到+4）。此外，你获得等同于基本速度的超自然飞行速度（机动性良好）。你只能在穿着轻甲或无甲时才能使用此能力。"
}
