{
    "key": "arcane pocket",
    "name": "Arcane Pocket",
    "url": "https://www.aonprd.com/SpellDisplay.aspx?ItemName=Arcane%20Pocket",
    "source": ["Black Markets pg. 27"],
    "school": "conjuration",
    "subSchools": ["creation"],
    "levels":     {
        "arcanist": 1,
        "sorcerer": 1,
        "wizard": 1
    },
    "castingTime": "1 standard action",
    "components": "V, F (a pocket and a silver button)",
    "range": "touch",
    "effect": "extradimensional space up to 1 cu. ft./level",
    "duration": "1 hour/level",
    "savingThrow": "none",
    "spellResistance": "no",
    "text": "With a touch, you conjure an extradimensional space inside a pouch or pocket. The pocket acts as a <i>bag of holding<\/i>, except it can hold only 10 pounds per caster level. Regardless of what is placed into the pocket, it weighs 3 pounds. Unlike a <i>bag of holding<\/i>, the pocket created by this ability cannot be overloaded or ruptured—any additional material simply spills out of the top—nor does it have any special interaction with other kinds of extradimensional spaces.<br><br> An <i>arcane pocket<\/i> grants you a +1 bonus on Sleight of Hand checks to conceal its contents. The pocket becomes nonmagical, spilling all of its contents onto the ground unharmed, if it leaves your possession or you create a new <i>arcane pocket<\/i>.",
    "name_zh": "祕法口袋",
    "castingTime_zh": "标准动作",
    "components_zh": "语言、器材 (一个口袋与一颗银钮扣)",
    "range_zh": "接触",
    "target_zh": "一立方尺/等级的异次元空间",
    "duration_zh": "1小时/等级",
    "savingThrow_zh": "无",
    "spellResistance_zh": "否",
    "text_zh": "<p>通过接触，你在一个袋子或口袋内部变出了个异次元空间。这口袋像次元袋(bag of holding)般作用，除了它能承载的只有每施法者等级10磅。不管什么东西放入了此口袋，它就重3磅。不像次元袋，经由此能力创造出来的口袋不能超重或破裂─任何其他的物品仅是从顶部散落─也不会与其它异次元物品有特殊互动。<\/p><p>一个祕法口袋给予你在隐藏它内部东西时巧手检定+1加值。当这口袋因为离开你的掌控或是你创造一个新的祕法口袋而变回原样后，口袋包含的东西都会无害的散落到地上。<\/p>"
}
