{
    "key": "cold iron fetters",
    "name": "Cold Iron Fetters",
    "url": "https://www.aonprd.com/SpellDisplay.aspx?ItemName=Cold%20Iron%20Fetters",
    "source": ["Legacy of the First World pg. 13"],
    "school": "conjuration",
    "subSchools": ["creation"],
    "levels":     {
        "arcanist": 5,
        "cleric": 5,
        "hunter": 3,
        "inquisitor": 4,
        "occultist": 5,
        "oracle": 5,
        "ranger": 3,
        "shaman": 5,
        "sorcerer": 5,
        "summoner": 4,
        "summoner (unchained)": 4,
        "warpriest": 5,
        "witch": 5,
        "wizard": 5
    },
    "castingTime": "1 standard action",
    "components": "V, S, M/DF (miniature cold iron shackle)",
    "range": "medium (100 ft. + 10 ft./level)",
    "target": "one creature",
    "duration": "1 round/level (D)",
    "savingThrow": "Reflex negates",
    "spellResistance": "no",
    "text": "Cold iron shackles materialize around the target’s limbs, reducing each of the target’s movement speeds by half. Any flying target has its maneuverability worsened by two steps (from good to poor, for example, to a minimum of clumsy maneuverability). Additionally, if the target has DR/cold iron or DR/cold iron and magic, it is unable to use supernatural or spell-like means of movement (such as <i>dimension door, teleport<\/i>, or <i>tree meld<\/i>) for the duration of the spell.",
    "name_zh": "寒铁之缚",
    "castingTime_zh": "标准动作",
    "components_zh": "语言, 姿势，材料/法器（寒铁镣铐模型）",
    "range_zh": "中距 (100尺+每等级10尺)",
    "target_zh": "一个生物",
    "duration_zh": "1轮/等级 (可解消)",
    "savingThrow_zh": "反射, 通过则无效",
    "spellResistance_zh": "否",
    "text_zh": "<p>寒铁的镣铐出现在目标腿的周围，将每一个目标的移动速度减半。任何飞行生物的机动性都将会下降两个级别（比如从良好到不良，机动性最差到笨拙）。除此之外，任何拥有DR/寒铁或者DR/寒铁与魔法的目标。它将不能在法术的持续时间内使用超自然能力或者类法术能力来进行移动（像是任意门，传送术，或者融身入树）。<\/p>"
}
