{
    "key": "horn of pursuit",
    "name": "Horn of Pursuit",
    "url": "https://www.aonprd.com/SpellDisplay.aspx?ItemName=Horn%20of%20Pursuit",
    "source": ["Ultimate Magic pg. 223"],
    "school": "evocation",
    "descriptors": ["sonic"],
    "levels":     {
        "bard": 1,
        "hunter": 1,
        "inquisitor": 1,
        "paladin": 1,
        "ranger": 1,
        "skald": 1
    },
    "castingTime": "1 standard action",
    "components": "S",
    "range": "personal",
    "effect": "3 peals of a horn",
    "duration": "1 round",
    "savingThrow": "none",
    "spellResistance": "no",
    "text": "You create the sound of a large hunting horn, blowing up to three notes as loud as a roaring dragon. These notes can be heard up to 2 miles away in typical outdoor conditions. You can make these sounds at any point during the spell’s duration as a free action, and each sounding can be short or long, allowing you to send very simple coded messages.",
    "name_zh": "集结号",
    "castingTime_zh": "标准动作",
    "components_zh": "姿势",
    "range_zh": "个人",
    "effect_zh": "三次号角声",
    "duration_zh": "1轮",
    "savingThrow_zh": "无",
    "spellResistance_zh": "否",
    "text_zh": "<p>你创造出巨型狩猎号角的声音，可以产生三个音符以及巨龙咆哮般的音量。声音可以在典型的户外条件下传出2英里之远。<\/p><p>你可以让这三次声音在法术持续的时间内以自由动作控制按任意节奏发出，可长可短，用以让你传递简短的讯息。<\/p>"
}
